intern/__init__.py
intern/remote/__init__.py
intern/remote/remote.py
intern/remote/boss/__init__.py
intern/remote/boss/remote.py
intern/remote/boss/tests/__init__.py
intern/remote/boss/tests/int_test_group_v1.py
intern/remote/boss/tests/int_test_metadata_v1.py
intern/remote/boss/tests/int_test_permission_v1.py
intern/remote/boss/tests/int_test_project_v1.py
intern/remote/boss/tests/int_test_user_role_v1.py
intern/remote/boss/tests/int_test_user_v1.py
intern/remote/boss/tests/int_test_volume_v1.py
intern/remote/boss/tests/test_remote.py
intern/remote/boss/tests/test_remote_get_cutout.py
intern/remote/boss/tests/test_remote_list.py
intern/resource/__init__.py
intern/resource/resource.py
intern/resource/boss/__init__.py
intern/resource/boss/resource.py
intern/resource/boss/tests/__init__.py
intern/resource/boss/tests/test_channel.py
intern/resource/boss/tests/test_collection.py
intern/resource/boss/tests/test_coord_frame.py
intern/resource/boss/tests/test_experiment.py
intern/service/__init__.py
intern/service/service.py
intern/service/boss/__init__.py
intern/service/boss/baseversion.py
intern/service/boss/httperrorlist.py
intern/service/boss/metadata.py
intern/service/boss/project.py
intern/service/boss/service.py
intern/service/boss/volume.py
intern/service/boss/tests/__init__.py
intern/service/boss/tests/test_baseversion.py
intern/service/boss/tests/test_volume.py
intern/service/boss/v1/__init__.py
intern/service/boss/v1/metadata.py
intern/service/boss/v1/project.py
intern/service/boss/v1/volume.py
intern/service/boss/v1/tests/__init__.py
intern/service/boss/v1/tests/test_group.py
intern/service/boss/v1/tests/test_metadata.py
intern/service/boss/v1/tests/test_project.py
intern/service/boss/v1/tests/test_user.py
intern/service/boss/v1/tests/test_user_role.py
intern/service/boss/v1/tests/test_volume.py
intern/utils/__init__.py
intern/utils/parallel.py
intern-0.9.12.dist-info/METADATA
intern-0.9.12.dist-info/WHEEL
intern-0.9.12.dist-info/top_level.txt
intern-0.9.12.dist-info/RECORD
