Metadata-Version: 2.1
Name: intern
Version: 0.9.12
Summary: Python SDK for interacting neuroscience data via the Boss API.
Home-page: https://github.com/jhuapl-boss/intern
Author: Johns Hopkins University Applied Physics Laboratory
Author-email: iarpamicrons@jhuapl.edu
License: Apache 2.0
Download-URL: https://github.com/jhuapl-boss/intern/tarball/0.9.12
Keywords: brain,microscopy,neuroscience,connectome,connectomics,spatial,EM,electron,calcium,database,boss,microns
Platform: UNKNOWN
Classifier: Development Status :: 4 - Beta
Classifier: Intended Audience :: Developers
Classifier: Programming Language :: Python :: 3.4
Classifier: Programming Language :: Python :: 3.5
Classifier: Programming Language :: Python :: 2.7
Requires-Dist: numpy
Requires-Dist: requests (>=2.11.1)
Requires-Dist: blosc (>=1.4.4)
Requires-Dist: six
Requires-Dist: mock
Requires-Dist: nose2
